{
    "result": "success",
    "msg": "",
    "data": [{
        "title": "游戏主播",
        "sub": [{
            "id": "1001",
            "name": "王者荣耀"
        }, {
            "id": "1002",
            "name": "英雄联盟"
        }, {
            "id": "1003",
            "name": "职业玩家"
        }, {
            "id": "1004",
            "name": "游戏解说"
        }]
    }, {
        "title": "娱乐/秀场",
        "sub": [{
            "id": "1005",
            "name": "唱歌"
        }, {
            "id": "1006",
            "name": "跳舞"
        }, {
            "id": "1007",
            "name": "娱乐主播"
        }]
    }, {
        "title": "其他",
        "sub": [{
            "id": "1008",
            "name": "户外主播"
        }, {
            "id": "1009",
            "name": "美食主播"
        }]
    }]
}